LICENSE
MANIFEST.in
README.md
setup.py
makecite/__init__.py
makecite/cmdline.py
makecite/discover.py
makecite/parsers.py
makecite.egg-info/PKG-INFO
makecite.egg-info/SOURCES.txt
makecite.egg-info/dependency_links.txt
makecite.egg-info/entry_points.txt
makecite.egg-info/requires.txt
makecite.egg-info/top_level.txt
makecite/bibfiles/astroml.bib
makecite/bibfiles/astropy.bib
makecite/bibfiles/cython.bib
makecite/bibfiles/emcee.bib
makecite/bibfiles/f2py.bib
makecite/bibfiles/gala.bib
makecite/bibfiles/ipython.bib
makecite/bibfiles/matplotlib.bib
makecite/bibfiles/numpy.bib
makecite/bibfiles/pandas.bib
makecite/bibfiles/schwimmbad.bib
makecite/bibfiles/scikit-image.bib
makecite/bibfiles/scikit-learn.bib
makecite/bibfiles/scipy.bib
makecite/bibfiles/seaborn.bib
makecite/bibfiles/skimage.bib
makecite/bibfiles/sklearn.bib
makecite/bibfiles/sympy.bib