Metadata-Version: 2.1
Name: makecite
Version: 0.5
Summary: Autogenerate bibtex citations for common Python packages
Home-page: https://github.com/adrn/makecite
Author: Adrian Price-Whelan, Alexandar Mechev, Julia Melo Rodrigues de Aguiar, Brigitta Sipocz, Leon Trapman
Author-email: adrn@astro.princeton.edu
License: UNKNOWN
Download-URL: https://github.com/adrn/makecite/archive/v0.0.1.tar.gz
Keywords: LaTeX,Astronomy,Citation,package management
Platform: UNKNOWN
Classifier: Development Status :: 1 - Planning
Classifier: Intended Audience :: Developers
Classifier: Intended Audience :: Science/Research
Classifier: License :: OSI Approved :: MIT License
Classifier: Natural Language :: English
Classifier: Topic :: Scientific/Engineering :: Astronomy
Classifier: Topic :: Text Processing :: Markup :: LaTeX
Classifier: Programming Language :: Python :: 3
Classifier: Programming Language :: Python :: 3.4
Classifier: Programming Language :: Python :: 3.5
Classifier: Programming Language :: Python :: 3.6
